{"editor_deps":{},"window_states":{"debug":false,"log":false},"windows":{"5468652160807109202":{"type":"PikchrEditor","fields":{"id":5468652160807109202,"target_svg":8439731964825661643,"visible":true,"content":"box\narrow\nbox","index":1,"error":null}},"8439731964825661643":{"type":"SvgWindow","fields":{"id":8439731964825661643,"owner_id":5468652160807109202,"svg_string":"<svg xmlns='http://www.w3.org/2000/svg' style='font-size:initial;' class=\"\" viewBox=\"0 0 292.32 76.32\" data-pikchr-date=\"20260102012653\"><style>text,path { font-family: 'Space Mono'; }</style>\n<path d=\"M2.16,74.16L110.16,74.16L110.16,2.16L2.16,2.16Z\"  style=\"fill:none;stroke-width:2.16;stroke:rgb(0,0,0);\" />\n<polygon points=\"182.16,38.16 170.64,42.48 170.64,33.84\" style=\"fill:rgb(0,0,0)\"/>\n<path d=\"M110.16,38.16L176.4,38.16\"  style=\"fill:none;stroke-width:2.16;stroke:rgb(0,0,0);\" />\n<path d=\"M182.16,74.16L290.16,74.16L290.16,2.16L182.16,2.16Z\"  style=\"fill:none;stroke-width:2.16;stroke:rgb(0,0,0);\" />\n</svg>\n","initial_size":{"x":300.0,"y":300.0},"prev_size":{"x":260.0,"y":226.0},"scale":1.5,"visible":true,"index":1}}}}